rori/__init__.py
rori/cli.py
rori/cli_utils.py
rori/config.py
rori/db.py
rori/k8s.py
rori/logger.py
rori/manager.py
rori/models.py
rori/service.py
rori/ui.py
rori/utils.py
rori/vw.py
rori/watcher.py
rori/command/__init__.py
rori/command/base.py
rori/command/kubernetes.py
rori/command/ssh.py
rori-0.0.2.dist-info/METADATA
rori-0.0.2.dist-info/WHEEL
rori-0.0.2.dist-info/entry_points.txt
rori-0.0.2.dist-info/top_level.txt
rori-0.0.2.dist-info/RECORD
