Metadata-Version: 2.4
Name: rori
Version: 0.0.2
Summary: Forward ports and track them with ease
Author-email: Misha Behersky <bmwant@gmail.com>
Project-URL: Homepage, https://github.com/pypa/sampleproject
Project-URL: Issues, https://github.com/pypa/sampleproject/issues
Classifier: Programming Language :: Python :: 3
Classifier: Operating System :: OS Independent
Requires-Python: <4.0,>=3.11
Requires-Dist: django-environ>=0.12.0
Requires-Dist: hapless>=0.11.1
Requires-Dist: rich<14.0.0,>=13.5.2
Requires-Dist: questionary>=2.0.0
Requires-Dist: kubernetes>=31.0.0
Requires-Dist: psutil>=6.1.0
Requires-Dist: loguru>=0.7.3
Provides-Extra: dev
Requires-Dist: pytest>=8.4.1; extra == "dev"
Requires-Dist: ruff>=0.12.7; extra == "dev"
Requires-Dist: twine>=6.1.0; extra == "dev"
